modulu.py
modulu-0.1.2.dist-info/licenses/LICENSE
modulu-0.1.2.dist-info/METADATA
modulu-0.1.2.dist-info/WHEEL
modulu-0.1.2.dist-info/top_level.txt
modulu-0.1.2.dist-info/RECORD
